{
  "annotations": {
    "list": [
      {
        "builtIn": 1,
        "datasource": {
          "type": "datasource",
          "uid": "grafana"
        },
        "enable": true,
        "hide": true,
        "iconColor": "rgba(0, 211, 255, 1)",
        "name": "Annotations & Alerts",
        "target": {
          "limit": 100,
          "matchAny": false,
          "tags": ["ryax"],
          "type": "dashboard"
        },
        "type": "dashboard"
      }
    ]
  },
  "description": "Details on Ryax Usage and Performances",
  "editable": true,
  "fiscalYearStartMonth": 0,
  "graphTooltip": 0,
  "id": 41,
  "links": [],
  "liveNow": false,
  "panels": [
    {
      "datasource": {
        "type": "prometheus",
        "uid": "prometheus"
      },
      "fieldConfig": {
        "defaults": {
          "color": {
            "mode": "thresholds"
          },
          "mappings": [],
          "min": 0,
          "thresholds": {
            "mode": "absolute",
            "steps": [
              {
                "color": "green",
                "value": null
              },
              {
                "color": "red",
                "value": 80
              }
            ]
          },
          "unit": "none"
        },
        "overrides": []
      },
      "gridPos": {
        "h": 24,
        "w": 9,
        "x": 0,
        "y": 0
      },
      "id": 11,
      "options": {
        "colorMode": "value",
        "graphMode": "area",
        "justifyMode": "auto",
        "orientation": "auto",
        "reduceOptions": {
          "calcs": [
            "last"
          ],
          "fields": "/.*/",
          "values": false
        },
        "textMode": "auto"
      },
      "pluginVersion": "10.1.1",
      "targets": [
        {
          "datasource": {
            "type": "prometheus",
            "uid": "prometheus"
          },
          "editorMode": "code",
          "exemplar": false,
          "expr": "sum by (site_name, node_pool_name) (ryax_action_deployments{state=~\"Running|Ready\", execution_type!=\"ActionExecutionType.DUMMY\"})",
          "format": "time_series",
          "instant": false,
          "interval": "",
          "legendFormat": "{{site_name}} / {{node_pool_name}}",
          "range": true,
          "refId": "A"
        }
      ],
      "title": "Running Actions (All sites)",
      "transformations": [
        {
          "id": "organize",
          "options": {
            "excludeByName": {
              "Time": true,
              "{node_pool_name=\"default\", site_name=\"local\"}": false
            },
            "indexByName": {
              "Time": 0,
              "Value": 3,
              "node_pool_name": 2,
              "site_name": 1
            },
            "renameByName": {
              "Value": "Deployed Actions",
              "node_pool_name": "Node Pool",
              "site_name": "Site"
            }
          }
        }
      ],
      "type": "stat"
    },
    {
      "datasource": {
        "type": "prometheus",
        "uid": "prometheus"
      },
      "fieldConfig": {
        "defaults": {
          "color": {
            "mode": "thresholds"
          },
          "custom": {
            "align": "auto",
            "cellOptions": {
              "type": "auto"
            },
            "inspect": false
          },
          "mappings": [
            {
              "options": {
                "0": {
                  "color": "semi-dark-blue",
                  "index": 1,
                  "text": "Down"
                },
                "1": {
                  "color": "semi-dark-purple",
                  "index": 0,
                  "text": "Up"
                }
              },
              "type": "value"
            }
          ],
          "thresholds": {
            "mode": "absolute",
            "steps": [
              {
                "color": "green",
                "value": null
              },
              {
                "color": "red",
                "value": 80
              }
            ]
          },
          "unit": "short"
        },
        "overrides": []
      },
      "gridPos": {
        "h": 8,
        "w": 11,
        "x": 9,
        "y": 0
      },
      "id": 6,
      "options": {
        "cellHeight": "sm",
        "footer": {
          "countRows": false,
          "fields": "",
          "reducer": [
            "sum"
          ],
          "show": false
        },
        "showHeader": true
      },
      "pluginVersion": "10.1.1",
      "targets": [
        {
          "datasource": {
            "type": "prometheus",
            "uid": "prometheus"
          },
          "editorMode": "code",
          "exemplar": false,
          "expr": "sum by (definition_id, name) (ryax_workflow_deployments{state=\"Running\"})",
          "format": "table",
          "instant": true,
          "interval": "",
          "legendFormat": "",
          "range": false,
          "refId": "A"
        }
      ],
      "title": "Workflow state",
      "transformations": [
        {
          "id": "organize",
          "options": {
            "excludeByName": {
              "Time": true,
              "Value": false,
              "name": false
            },
            "indexByName": {
              "Time": 0,
              "Value": 3,
              "definition_id": 2,
              "name": 1
            },
            "renameByName": {
              "Test scaling - 9f856720-7018-42a3-a47b-7ecfe7ab65c3": "",
              "Time": ""
            }
          }
        }
      ],
      "type": "table"
    },
    {
      "datasource": {
        "type": "prometheus",
        "uid": "prometheus"
      },
      "fieldConfig": {
        "defaults": {
          "color": {
            "mode": "thresholds"
          },
          "mappings": [],
          "min": 0,
          "thresholds": {
            "mode": "absolute",
            "steps": [
              {
                "color": "super-light-purple",
                "value": null
              },
              {
                "color": "yellow",
                "value": 30
              },
              {
                "color": "red",
                "value": 50
              }
            ]
          }
        },
        "overrides": []
      },
      "gridPos": {
        "h": 8,
        "w": 4,
        "x": 20,
        "y": 0
      },
      "id": 13,
      "options": {
        "orientation": "auto",
        "reduceOptions": {
          "calcs": [
            "lastNotNull"
          ],
          "fields": "",
          "values": false
        },
        "showThresholdLabels": false,
        "showThresholdMarkers": true
      },
      "pluginVersion": "10.1.1",
      "targets": [
        {
          "datasource": {
            "type": "prometheus",
            "uid": "prometheus"
          },
          "exemplar": true,
          "expr": "sum by (project_id) (ryax_workflow_deployments{state=\"Running\"})",
          "interval": "",
          "legendFormat": "",
          "refId": "A"
        }
      ],
      "title": "Workflows Deployed",
      "type": "gauge"
    },
    {
      "datasource": {
        "type": "prometheus",
        "uid": "prometheus"
      },
      "fieldConfig": {
        "defaults": {
          "color": {
            "mode": "palette-classic"
          },
          "custom": {
            "axisCenteredZero": false,
            "axisColorMode": "text",
            "axisLabel": "",
            "axisPlacement": "auto",
            "axisSoftMin": 0,
            "barAlignment": 0,
            "drawStyle": "line",
            "fillOpacity": 87,
            "gradientMode": "none",
            "hideFrom": {
              "legend": false,
              "tooltip": false,
              "viz": false
            },
            "insertNulls": false,
            "lineInterpolation": "stepBefore",
            "lineWidth": 0,
            "pointSize": 5,
            "scaleDistribution": {
              "type": "linear"
            },
            "showPoints": "never",
            "spanNulls": false,
            "stacking": {
              "group": "A",
              "mode": "normal"
            },
            "thresholdsStyle": {
              "mode": "off"
            }
          },
          "decimals": 0,
          "mappings": [],
          "thresholds": {
            "mode": "absolute",
            "steps": [
              {
                "color": "green",
                "value": null
              },
              {
                "color": "red",
                "value": 80
              }
            ]
          },
          "unit": "none"
        },
        "overrides": []
      },
      "gridPos": {
        "h": 8,
        "w": 11,
        "x": 9,
        "y": 8
      },
      "id": 12,
      "options": {
        "legend": {
          "calcs": [
            "max"
          ],
          "displayMode": "table",
          "placement": "right",
          "showLegend": true
        },
        "tooltip": {
          "mode": "multi",
          "sort": "none"
        }
      },
      "targets": [
        {
          "datasource": {
            "type": "prometheus",
            "uid": "prometheus"
          },
          "disableTextWrap": false,
          "editorMode": "code",
          "expr": "sum by(name, site_name, node_pool_name) (ryax_action_deployments{state=~\"Ready|Running\", execution_type!=\"ActionExecutionType.DUMMY\"}) > 0",
          "fullMetaSearch": false,
          "includeNullMetadata": true,
          "instant": false,
          "legendFormat": "{{name}} ({{site_name}}/{{node_pool_name}})",
          "range": true,
          "refId": "A",
          "useBackend": false
        }
      ],
      "title": "Deployed Actions",
      "type": "timeseries"
    },
    {
      "datasource": {
        "type": "prometheus",
        "uid": "prometheus"
      },
      "fieldConfig": {
        "defaults": {
          "color": {
            "mode": "thresholds"
          },
          "mappings": [],
          "min": 0,
          "thresholds": {
            "mode": "absolute",
            "steps": [
              {
                "color": "semi-dark-purple",
                "value": null
              },
              {
                "color": "yellow",
                "value": 30
              },
              {
                "color": "red",
                "value": 50
              }
            ]
          }
        },
        "overrides": []
      },
      "gridPos": {
        "h": 8,
        "w": 4,
        "x": 20,
        "y": 8
      },
      "id": 8,
      "options": {
        "orientation": "auto",
        "reduceOptions": {
          "calcs": [
            "lastNotNull"
          ],
          "fields": "",
          "values": false
        },
        "showThresholdLabels": false,
        "showThresholdMarkers": true
      },
      "pluginVersion": "10.1.1",
      "targets": [
        {
          "datasource": {
            "type": "prometheus",
            "uid": "prometheus"
          },
          "editorMode": "code",
          "exemplar": true,
          "expr": "sum by (project_id) (ryax_action_deployments{state=\"Running\"})",
          "interval": "",
          "legendFormat": "",
          "range": true,
          "refId": "A"
        }
      ],
      "title": "Action Deployed",
      "type": "gauge"
    },
    {
      "datasource": {
        "type": "prometheus",
        "uid": "prometheus"
      },
      "fieldConfig": {
        "defaults": {
          "color": {
            "mode": "palette-classic"
          },
          "custom": {
            "axisCenteredZero": false,
            "axisColorMode": "text",
            "axisGridShow": true,
            "axisLabel": "",
            "axisPlacement": "auto",
            "axisSoftMin": 0,
            "barAlignment": -1,
            "drawStyle": "line",
            "fillOpacity": 11,
            "gradientMode": "none",
            "hideFrom": {
              "legend": false,
              "tooltip": false,
              "viz": false
            },
            "insertNulls": false,
            "lineInterpolation": "smooth",
            "lineWidth": 2,
            "pointSize": 5,
            "scaleDistribution": {
              "type": "linear"
            },
            "showPoints": "auto",
            "spanNulls": false,
            "stacking": {
              "group": "A",
              "mode": "none"
            },
            "thresholdsStyle": {
              "mode": "off"
            }
          },
          "decimals": 0,
          "mappings": [],
          "min": 0,
          "thresholds": {
            "mode": "absolute",
            "steps": [
              {
                "color": "green",
                "value": null
              },
              {
                "color": "red",
                "value": 80
              }
            ]
          },
          "unit": "none"
        },
        "overrides": [
          {
            "__systemRef": "hideSeriesFrom",
            "matcher": {
              "id": "byNames",
              "options": {
                "mode": "exclude",
                "names": [
                  "Allocated ",
                  "Created ",
                  "Pending ",
                  "Running "
                ],
                "prefix": "All except:",
                "readOnly": true
              }
            },
            "properties": [
              {
                "id": "custom.hideFrom",
                "value": {
                  "legend": false,
                  "tooltip": false,
                  "viz": true
                }
              }
            ]
          }
        ]
      },
      "gridPos": {
        "h": 8,
        "w": 11,
        "x": 9,
        "y": 16
      },
      "id": 10,
      "options": {
        "legend": {
          "calcs": [
            "max"
          ],
          "displayMode": "list",
          "placement": "right",
          "showLegend": true
        },
        "tooltip": {
          "mode": "single",
          "sort": "none"
        }
      },
      "pluginVersion": "8.4.2",
      "targets": [
        {
          "datasource": {
            "type": "prometheus",
            "uid": "prometheus"
          },
          "editorMode": "code",
          "exemplar": true,
          "expr": "sum by (state) (ryax_execution_connections{state!~\"Completed|Canceled\"})",
          "interval": "",
          "legendFormat": "{{state}} ",
          "range": true,
          "refId": "A"
        }
      ],
      "title": "Execution Connections",
      "type": "timeseries"
    },
    {
      "datasource": {
        "type": "prometheus",
        "uid": "prometheus"
      },
      "fieldConfig": {
        "defaults": {
          "color": {
            "mode": "thresholds"
          },
          "mappings": [],
          "min": 0,
          "thresholds": {
            "mode": "absolute",
            "steps": [
              {
                "color": "semi-dark-blue",
                "value": null
              },
              {
                "color": "yellow",
                "value": 30
              },
              {
                "color": "red",
                "value": 50
              }
            ]
          }
        },
        "overrides": []
      },
      "gridPos": {
        "h": 8,
        "w": 4,
        "x": 20,
        "y": 16
      },
      "id": 14,
      "options": {
        "orientation": "auto",
        "reduceOptions": {
          "calcs": [
            "lastNotNull"
          ],
          "fields": "",
          "values": false
        },
        "showThresholdLabels": false,
        "showThresholdMarkers": true
      },
      "pluginVersion": "10.1.1",
      "targets": [
        {
          "datasource": {
            "type": "prometheus",
            "uid": "prometheus"
          },
          "editorMode": "code",
          "exemplar": true,
          "expr": "sum by (project_id) (ryax_execution_connections{state=\"Running\"})",
          "interval": "",
          "legendFormat": "",
          "range": true,
          "refId": "A"
        }
      ],
      "title": "Running Executions",
      "type": "gauge"
    },
    {
      "datasource": {
        "type": "prometheus",
        "uid": "prometheus"
      },
      "fieldConfig": {
        "defaults": {
          "color": {
            "mode": "palette-classic"
          },
          "custom": {
            "axisCenteredZero": false,
            "axisColorMode": "text",
            "axisLabel": "Seconds",
            "axisPlacement": "auto",
            "axisSoftMin": 0,
            "barAlignment": 0,
            "drawStyle": "line",
            "fillOpacity": 0,
            "gradientMode": "none",
            "hideFrom": {
              "legend": false,
              "tooltip": false,
              "viz": false
            },
            "insertNulls": false,
            "lineInterpolation": "linear",
            "lineWidth": 1,
            "pointSize": 5,
            "scaleDistribution": {
              "type": "linear"
            },
            "showPoints": "auto",
            "spanNulls": false,
            "stacking": {
              "group": "A",
              "mode": "none"
            },
            "thresholdsStyle": {
              "mode": "line"
            }
          },
          "mappings": [],
          "thresholds": {
            "mode": "absolute",
            "steps": [
              {
                "color": "green",
                "value": null
              },
              {
                "color": "semi-dark-blue",
                "value": 0.5
              },
              {
                "color": "#EAB839",
                "value": 1
              },
              {
                "color": "red",
                "value": 2
              }
            ]
          }
        },
        "overrides": []
      },
      "gridPos": {
        "h": 11,
        "w": 8,
        "x": 0,
        "y": 24
      },
      "id": 4,
      "options": {
        "legend": {
          "calcs": [],
          "displayMode": "list",
          "placement": "bottom",
          "showLegend": true
        },
        "tooltip": {
          "mode": "single",
          "sort": "none"
        }
      },
      "targets": [
        {
          "datasource": {
            "type": "prometheus",
            "uid": "prometheus"
          },
          "editorMode": "code",
          "exemplar": true,
          "expr": "histogram_quantile(0.90, sum(rate(ryax_user_api_requests_duration_seconds_bucket[2m])) by (ryax_user_api_http_path, ryax_user_api_http_method, ryax_project, le))",
          "interval": "",
          "legendFormat": "{{ryax_user_api_http_method}} {{ryax_user_api_http_path}}",
          "range": true,
          "refId": "A"
        }
      ],
      "title": "User API Request Processing Time 90th quantile",
      "type": "timeseries"
    },
    {
      "datasource": {
        "type": "prometheus",
        "uid": "prometheus"
      },
      "description": "Internal Ryax event processing time quantile",
      "fieldConfig": {
        "defaults": {
          "color": {
            "mode": "palette-classic"
          },
          "custom": {
            "axisCenteredZero": false,
            "axisColorMode": "text",
            "axisLabel": "",
            "axisPlacement": "auto",
            "barAlignment": 0,
            "drawStyle": "line",
            "fillOpacity": 0,
            "gradientMode": "none",
            "hideFrom": {
              "legend": false,
              "tooltip": false,
              "viz": false
            },
            "insertNulls": false,
            "lineInterpolation": "smooth",
            "lineWidth": 1,
            "pointSize": 5,
            "scaleDistribution": {
              "type": "linear"
            },
            "showPoints": "auto",
            "spanNulls": false,
            "stacking": {
              "group": "A",
              "mode": "none"
            },
            "thresholdsStyle": {
              "mode": "area"
            }
          },
          "mappings": [],
          "thresholds": {
            "mode": "absolute",
            "steps": [
              {
                "color": "green",
                "value": null
              },
              {
                "color": "red",
                "value": 0.1
              }
            ]
          },
          "unit": "s"
        },
        "overrides": []
      },
      "gridPos": {
        "h": 11,
        "w": 16,
        "x": 8,
        "y": 24
      },
      "id": 2,
      "options": {
        "legend": {
          "calcs": [
            "max",
            "min"
          ],
          "displayMode": "table",
          "placement": "right",
          "showLegend": true,
          "sortBy": "Max",
          "sortDesc": true
        },
        "tooltip": {
          "mode": "single",
          "sort": "none"
        }
      },
      "pluginVersion": "8.4.2",
      "targets": [
        {
          "datasource": {
            "type": "prometheus",
            "uid": "prometheus"
          },
          "editorMode": "code",
          "exemplar": false,
          "expr": "histogram_quantile(0.90, sum(rate(ryax_events_processing_time_seconds_bucket[2m])) by (event_name, le, handler_name)) > 0",
          "format": "time_series",
          "instant": false,
          "interval": "",
          "legendFormat": "{{event_name}} ({{handler_name}})",
          "range": true,
          "refId": "A"
        }
      ],
      "title": "Events processin time 90th quantile",
      "type": "timeseries"
    }
  ],
  "refresh": "10s",
  "schemaVersion": 38,
  "style": "dark",
  "tags": [],
  "templating": {
    "list": []
  },
  "time": {
    "from": "now-30m",
    "to": "now"
  },
  "timepicker": {},
  "timezone": "",
  "title": "Ryax Usage and Performance",
  "uid": "f615b285-8dd9-45c7-b4bf-1f98d5b87b0a",
  "version": 5,
  "weekStart": ""
}
